TemplateGitHub/TemplateGitHub.py
TemplateGitHub/Utils.py
TemplateGitHub/__init__.py
TemplateGitHub-0.0.1.dist-info/LICENSE
TemplateGitHub-0.0.1.dist-info/METADATA
TemplateGitHub-0.0.1.dist-info/WHEEL
TemplateGitHub-0.0.1.dist-info/top_level.txt
TemplateGitHub-0.0.1.dist-info/RECORD
