Metadata-Version: 2.1
Name: TemplateGitHub
Version: 0.0.1
Summary: A package containing a dog
Home-page: https://github.com/drbmrp/TemplateGitHub/
Author: drbmrp
Author-email: borja.rojo.perez@gmail.com
License: LICENSE.txt
Platform: UNKNOWN
Classifier: Programming Language :: Python :: 3.7
Classifier: License :: OSI Approved :: GNU General Public License v3 (GPLv3)
Requires-Dist: numpy (>=1.0)
